buses_warsaw/__init__.py
buses_warsaw/buses.py
buses_warsaw/example.ipynb
buses_warsaw/map.png
buses_warsaw/.ipynb_checkpoints/Untitled-checkpoint.ipynb
buses_warsaw/.ipynb_checkpoints/example-checkpoint.ipynb
buses_warsaw/data/bus_stops_0.txt
buses_warsaw/data/data_0.txt
buses_warsaw/data/data_1.txt
buses_warsaw/data/data_10.txt
buses_warsaw/data/data_11.txt
buses_warsaw/data/data_12.txt
buses_warsaw/data/data_13.txt
buses_warsaw/data/data_14.txt
buses_warsaw/data/data_15.txt
buses_warsaw/data/data_16.txt
buses_warsaw/data/data_17.txt
buses_warsaw/data/data_18.txt
buses_warsaw/data/data_19.txt
buses_warsaw/data/data_2.txt
buses_warsaw/data/data_3.txt
buses_warsaw/data/data_4.txt
buses_warsaw/data/data_5.txt
buses_warsaw/data/data_6.txt
buses_warsaw/data/data_7.txt
buses_warsaw/data/data_8.txt
buses_warsaw/data/data_9.txt
buses_warsaw/data/schedule_7009_01_523_0.txt
buseswarsaw-1.0.1.dist-info/DESCRIPTION.rst
buseswarsaw-1.0.1.dist-info/METADATA
buseswarsaw-1.0.1.dist-info/RECORD
buseswarsaw-1.0.1.dist-info/WHEEL
buseswarsaw-1.0.1.dist-info/metadata.json
buseswarsaw-1.0.1.dist-info/top_level.txt
