Metadata-Version: 2.0
Name: buseswarsaw
Version: 1.0.1
Summary: Python package containing tools for analysing data on buses in Warsaw
Home-page: https://github.com/BDomzal/buses-in-Warsaw-bd
Author: Barbara Domżał
License: MIT
Platform: UNKNOWN
Classifier: License :: OSI Approved :: MIT License
Classifier: Programming Language :: Python :: 3
Classifier: Programming Language :: Python :: 3.6
Requires-Dist: numpy
Requires-Dist: pandas
Requires-Dist: geopy
Requires-Dist: matplotlib
